priodecode/prio_decoder.vhdl
library ieee;
use IEEE.std_logic_1164.all;
use IEEE.numeric_std.all;

entity prio_decoder is
    port(
        signal k: in std_logic_vector(6 downto 0);
        signal o: out std_logic_vector(2 downto 0)
    );
end prio_decoder;

architecture behave of prio_decoder is
begin
    process(k)
    begin
        if k = (k'range => '0') then 
            o <= std_logic_vector(to_unsigned(0, 3));
        elsif k = "0000001" then
            o <=  std_logic_vector(to_unsigned(1, 3));
        elsif k = "0000011" then
            o <=  std_logic_vector(to_unsigned(2, 3));
        elsif k = "0000111" then
            o <=  std_logic_vector(to_unsigned(3, 3));
        elsif k = "0001111" then
            o <=  std_logic_vector(to_unsigned(4, 3));
        elsif k = "0011111" then
            o <=  std_logic_vector(to_unsigned(5, 3));
        elsif k = "0111111" then
            o <=  std_logic_vector(to_unsigned(6, 3));
        elsif k = (k'range => '1') then
            o <=  std_logic_vector(to_unsigned(7, 3));
        end if;
    end process;
end behave;

priodecode/prio_decoder_tb.vhdl
library ieee;
use IEEE.std_logic_1164.all;
use IEEE.numeric_std.all;

entity prio_decoder_tb is
end prio_decoder_tb;

architecture test of prio_decoder_tb is
    component prio_decoder
        port
            (
                signal k: in std_logic_vector(6 downto 0);
                signal o: out std_logic_vector(2 downto 0)
            );
    end component;
    signal k: std_logic_vector(6 downto 0);
    signal o: std_logic_vector(2 downto 0);
begin
    pd: prio_decoder port map 
        (k => k, o => o);
    process
    begin
        wait for 1 ns;
        k <= (k'range =>  '0');
        wait for 1 ns;
        k <= "0000001";
        wait for 1 ns;
        k <= "0000011";
        wait for 1 ns;
        k <= "0000111";
        wait for 1 ns;
        k <= "0001111";
        wait for 1 ns;
        k <= "0011111";
        wait for 1 ns;
        k <= "0111111";
        wait for 1 ns;
        k <= "1111111";
        wait for 1 ns;
        assert false report "Testbench beendet";
        wait;
    end process;
end test;

priodecode/result.vcd
$date
  Mon Jun 19 20:04:14 2023
$end
$version
  GHDL v0
$end
$timescale
  1 fs
$end
$scope module standard $end
$upscope $end
$scope module std_logic_1164 $end
$upscope $end
$scope module numeric_std $end
$upscope $end
$scope module prio_decoder_tb $end
$var reg 7 ! k[6:0] $end
$var reg 3 " o[2:0] $end
$scope module pd $end
$var reg 7 # k[6:0] $end
$var reg 3 $ o[2:0] $end
$upscope $end
$upscope $end
$enddefinitions $end
#0
bUUUUUUU !
bUUU "
bUUUUUUU #
bUUU $
#1000000
b0000000 !
b000 "
b0000000 #
b000 $
#2000000
b0000001 !
b001 "
b0000001 #
b001 $
#3000000
b0000011 !
b010 "
b0000011 #
b010 $
#4000000
b0000111 !
b011 "
b0000111 #
b011 $
#5000000
b0001111 !
b100 "
b0001111 #
b100 $
#6000000
b0011111 !
b101 "
b0011111 #
b101 $
#7000000
b0111111 !
b110 "
b0111111 #
b110 $
#8000000
b1111111 !
b111 "
b1111111 #
b111 $
